sit4tfjs/__init__.py
sit4tfjs/browser_runtime.py
sit4tfjs/core.py
sit4tfjs/main.py
sit4tfjs/tfjs_runtime.py
sit4tfjs/utils.py
sit4tfjs-1.0.0.dist-info/licenses/LICENSE
sit4tfjs-1.0.0.dist-info/METADATA
sit4tfjs-1.0.0.dist-info/WHEEL
sit4tfjs-1.0.0.dist-info/entry_points.txt
sit4tfjs-1.0.0.dist-info/top_level.txt
sit4tfjs-1.0.0.dist-info/RECORD
