Metadata-Version: 2.4
Name: sit4tfjs
Version: 1.0.0
Summary: Simple Inference Test for TensorFlow.js. A benchmark inference speed testing tool for TensorFlow.js models.
Home-page: https://github.com/PINTO0309/sit4tfjs
Author: Katsuya Hyodo
Author-email: Katsuya Hyodo <rmsdh122@yahoo.co.jp>
Maintainer-email: Katsuya Hyodo <rmsdh122@yahoo.co.jp>
License: MIT
Project-URL: Homepage, https://github.com/PINTO0309/sit4tfjs
Project-URL: Repository, https://github.com/PINTO0309/sit4tfjs.git
Keywords: tensorflow,tensorflowjs,tfjs,benchmark,inference,performance,testing,deep learning,machine learning,neural network
Platform: linux
Platform: unix
Platform: windows
Platform: macos
Classifier: Development Status :: 5 - Production/Stable
Classifier: Intended Audience :: Developers
Classifier: Intended Audience :: Education
Classifier: Intended Audience :: Information Technology
Classifier: Intended Audience :: Science/Research
Classifier: License :: OSI Approved :: MIT License
Classifier: Operating System :: OS Independent
Classifier: Programming Language :: Python :: 3
Classifier: Programming Language :: Python :: 3.10
Classifier: Programming Language :: Python :: 3.11
Classifier: Programming Language :: Python :: 3.12
Classifier: Topic :: Scientific/Engineering
Classifier: Topic :: Scientific/Engineering :: Artificial Intelligence
Classifier: Topic :: Software Development :: Libraries :: Python Modules
Requires-Python: >=3.8
License-File: LICENSE
Requires-Dist: numpy>=1.19.0
Requires-Dist: tensorflowjs>=4.0.0
Requires-Dist: rich>=10.0.0
Requires-Dist: psutil>=5.8.0
Provides-Extra: tensorflow
Requires-Dist: tensorflow>=2.10.0; extra == "tensorflow"
Provides-Extra: dev
Requires-Dist: pytest>=6.0; extra == "dev"
Requires-Dist: pytest-cov; extra == "dev"
Requires-Dist: black; extra == "dev"
Requires-Dist: flake8; extra == "dev"
Requires-Dist: mypy; extra == "dev"
Dynamic: author
Dynamic: home-page
Dynamic: license-file
Dynamic: platform
Dynamic: requires-python
